rdassemblydis/EcsInterface.py
rdassemblydis/__init__.py
rdassemblydis/mainModel.py
rdassemblydis/metadata.py
rdassemblydis/operation.py
rdassemblydis/utility.py
rdassemblydis-1.1.9.dist-info/METADATA
rdassemblydis-1.1.9.dist-info/WHEEL
rdassemblydis-1.1.9.dist-info/top_level.txt
rdassemblydis-1.1.9.dist-info/RECORD
